setup.py
rafsun_distributions/Binomialdistribution.py
rafsun_distributions/Gaussiandistribution.py
rafsun_distributions/Generaldistribution.py
rafsun_distributions/__init__.py
rafsun_dst.egg-info/PKG-INFO
rafsun_dst.egg-info/SOURCES.txt
rafsun_dst.egg-info/dependency_links.txt
rafsun_dst.egg-info/not-zip-safe
rafsun_dst.egg-info/top_level.txt